pferret/__init__.py
pferret/wrapper.py
pferret/lib/go.mod
pferret/lib/go.sum
pferret/lib/libferret.h
pferret/lib/libferret.so
pferret/lib/main.go
pythonferret-0.1.1.data/data/go-file/main.go
pythonferret-0.1.1.data/data/go-mod-file/go.mod
pythonferret-0.1.1.data/data/go-sum-file/go.sum
pythonferret-0.1.1.data/data/header-file/libferret.h
pythonferret-0.1.1.data/data/so-file/libferret.so
pythonferret-0.1.1.dist-info/LICENSE
pythonferret-0.1.1.dist-info/METADATA
pythonferret-0.1.1.dist-info/WHEEL
pythonferret-0.1.1.dist-info/top_level.txt
pythonferret-0.1.1.dist-info/RECORD
